setup.py
hyzeeck_distributions/Binomialdistribution.py
hyzeeck_distributions/Gaussiandistribution.py
hyzeeck_distributions/Generaldistribution.py
hyzeeck_distributions/__init__.py
hyzeeck_distributions.egg-info/PKG-INFO
hyzeeck_distributions.egg-info/SOURCES.txt
hyzeeck_distributions.egg-info/dependency_links.txt
hyzeeck_distributions.egg-info/not-zip-safe
hyzeeck_distributions.egg-info/top_level.txt