Metadata-Version: 1.0
Name: hyzeeck-distributions
Version: 0.1
Summary: Gaussian distributions
Home-page: UNKNOWN
Author: Rufai Isaac
Author-email: hyzeeck234@gmail.com
License: UNKNOWN
Platform: UNKNOWN
